rostran/__init__.py
rostran/cli/__init__.py
rostran/cli/__main__.py
rostran/core/__init__.py
rostran/core/conditions.py
rostran/core/exceptions.py
rostran/core/format.py
rostran/core/mappings.py
rostran/core/metadata.py
rostran/core/outputs.py
rostran/core/parameters.py
rostran/core/properties.py
rostran/core/reporter.py
rostran/core/resources.py
rostran/core/rule_manager.py
rostran/core/rules.py
rostran/core/settings.py
rostran/core/template.py
rostran/core/utils.py
rostran/core/workspace.py
rostran/handlers/__init__.py
rostran/handlers/basic.py
rostran/handlers/merge.py
rostran/handlers/resource.py
rostran/providers/__init__.py
rostran/providers/cloudformation/__init__.py
rostran/providers/cloudformation/template.py
rostran/providers/excel/__init__.py
rostran/providers/excel/template.py
rostran/providers/ros/__init__.py
rostran/providers/ros/functions.py
rostran/providers/ros/template.py
rostran/providers/ros/yaml_util.py
rostran/providers/terraform/__init__.py
rostran/providers/terraform/c_template.py
rostran/providers/terraform/template.py
rostran/providers/terraform/template_blocks.py
rostran/rules/cloudformation/builtin/association_property.yml
rostran/rules/cloudformation/builtin/function.yml
rostran/rules/cloudformation/builtin/meta_data.yml
rostran/rules/cloudformation/builtin/pseudo_parameters.yml
rostran/rules/cloudformation/resource/aws_acmpca_certificate.yml
rostran/rules/cloudformation/resource/aws_api_gateway_deployment.yml
rostran/rules/cloudformation/resource/aws_api_gateway_v2_api.yml
rostran/rules/cloudformation/resource/aws_api_gateway_v2_deployment.yml
rostran/rules/cloudformation/resource/aws_auto_scaling_auto_scaling_group.yml
rostran/rules/cloudformation/resource/aws_auto_scaling_launch_configuration.yml
rostran/rules/cloudformation/resource/aws_auto_scaling_lifecycle_hook.yml
rostran/rules/cloudformation/resource/aws_auto_scaling_scaling_policy.yml
rostran/rules/cloudformation/resource/aws_cloud_formation_custom_resource.yml
alibabacloud_ros_tran-0.20.0.dist-info/LICENSE
alibabacloud_ros_tran-0.20.0.dist-info/METADATA
alibabacloud_ros_tran-0.20.0.dist-info/WHEEL
alibabacloud_ros_tran-0.20.0.dist-info/entry_points.txt
alibabacloud_ros_tran-0.20.0.dist-info/top_level.txt
alibabacloud_ros_tran-0.20.0.dist-info/RECORD
