Metadata-Version: 2.1
Name: alibabacloud-ros-tran
Version: 0.20.0
Summary: Resource Orchestration Service Template Transformer.
Home-page: https://www.alibabacloud.com/product/ros
Author: AlibabaCloud
Author-email: aliyun-developers-efficiency@list.alibaba-inc.com
License: Apache License 2.0
Keywords: alibabacloud,aliyun,ros,transformer,template
Platform: any
Classifier: Intended Audience :: Developers
Classifier: License :: OSI Approved :: Apache Software License
Classifier: Programming Language :: Python
Classifier: Programming Language :: Python :: 3
Classifier: Programming Language :: Python :: 3.7
Classifier: Programming Language :: Python :: 3.8
Classifier: Programming Language :: Python :: 3.9
Classifier: Programming Language :: Python :: 3.10
Classifier: Programming Language :: Python :: 3.11
Classifier: Programming Language :: Python :: 3.12
Classifier: Topic :: Software Development :: Libraries
Classifier: Operating System :: MacOS :: MacOS X
Classifier: Operating System :: POSIX
Classifier: Operating System :: POSIX :: BSD
Classifier: Operating System :: POSIX :: Linux
Classifier: Operating System :: Microsoft :: Windows
Requires-Python: >=3.7.0
License-File: LICENSE
Requires-Dist: colorama (<1.0.0,>=0.4.0)
Requires-Dist: libterraform (<1.0.0,>=0.7.0)
Requires-Dist: openpyxl (==3.*)
Requires-Dist: ruamel.yaml (>=0.17.0)
Requires-Dist: typer (<1.0.0,>=0.6.0)
